extralearning/VERSION
extralearning/__init__.py
extralearning/supervised/__init__.py
extralearning/supervised/__models.py
extralearning/supervised/classification.py
extralearning/supervised/estimatorclass.py
extralearning/supervised/regression.py
extralearning/supervised/summaryclass.py
extralearning-0.0.0.dist-info/METADATA
extralearning-0.0.0.dist-info/WHEEL
extralearning-0.0.0.dist-info/top_level.txt
extralearning-1.1.0.dist-info/METADATA
extralearning-1.1.0.dist-info/WHEEL
extralearning-1.1.0.dist-info/top_level.txt
extralearning-1.1.0.dist-info/RECORD
