Metadata-Version: 2.1
Name: extralearning
Version: 1.1.0
Summary: extralearning is a comprehensive package that consolidates leading ML frameworks and introduces functionality to streamline code in ML projects.
Home-page: https://github.com/extra-learning/extralearning
Author: Liam Arguedas
Author-email: iliamftw2013@gmail.com
License: BSD 3 clause
Classifier: License :: OSI Approved :: BSD License
Classifier: Programming Language :: Python :: 3.8
Classifier: Programming Language :: Python :: 3.9
Classifier: Programming Language :: Python :: 3.10
Classifier: Programming Language :: Python :: 3.11
Requires-Python: >=3.8.0
Requires-Dist: numpy (>=1.24.3)
Requires-Dist: pandas (>=1.5.3)
Requires-Dist: scikit-learn (>=1.3.0)
Requires-Dist: xgboost (>=1.7.6)
Requires-Dist: lightgbm (>=4.0.0)
Requires-Dist: catboost (>=1.2.1)
